nooploop_uwb/__init__.py
nooploop_uwb/aoa.py
nooploop_uwb/utils/nooploop_uwb_helper.py
nooploop_uwb-0.0.1.dist-info/LICENSE
nooploop_uwb-0.0.1.dist-info/METADATA
nooploop_uwb-0.0.1.dist-info/WHEEL
nooploop_uwb-0.0.1.dist-info/top_level.txt
nooploop_uwb-0.0.1.dist-info/RECORD
