Metadata-Version: 2.1
Name: nooploop-uwb
Version: 0.0.1
Summary: Nooploop LinkTrack UWB Products Python API.
Home-page: https://github.com/JaySurplus/nooploop_uwb
Author: JaySurplus
Author-email: znznbest2004@gmail.com
License: MIT
Download-URL: https://github.com/JaySurplus/nooploop_uwb/releases
Platform: Ubuntu 20.04
Platform: Ubuntu 18.04*
Platform: Ubuntu 16.04*
Platform: Windows 10
Classifier: Programming Language :: Python :: 3
Classifier: License :: OSI Approved :: MIT License
Classifier: Operating System :: OS Independent
Requires-Python: >=3.6
Requires-Dist: pyserial (>=3.4)
